{
  "project_info": {
    "project_number": "124817059380",
    "project_id": "contactmanagement-6820d",
    "storage_bucket": "contactmanagement-6820d.firebasestorage.app"
  },
  "client": [
    {
      "client_info": {
        "mobilesdk_app_id": "1:124817059380:android:45b16382043c374b3b2461",
        "android_client_info": {
          "package_name": "com.example.stock_maintain"
        }
      },
      "oauth_client": [],
      "api_key": [
        {
          "current_key": "AIzaSyDAWIDxQwDgfBdoBV7BiaKA-sF3t9XLlMI"
        }
      ],
      "services": {
        "appinvite_service": {
          "other_platform_oauth_client": []
        }
      }
    }
  ],
  "configuration_version": "1"
}